{"checked": ["Calico (company)", "Bluebird bio", "Alphabet Inc.", "Biotechnology industry in Boston", "Antibody Solutions", "ARIAD Pharmaceuticals", "Biobot Analytics", "Amgen", "CD Genomics", "Cephalon (company)", "Biosearch Technologies", "BRT Laboratories", "BioTork", "Avecia", "Alnylam Pharmaceuticals", "CoTherix", "Complete Genomics", "Genentech", "Axial Biotech", "Abgent", "3Scan", "Altos Labs", "Amicus Therapeutics", "Celgene", "Clear Labs", "Applied Biosystems", "Biomatrica", "CPC Scientific", "Bristol Myers Squibb", "Arrakis Therapeutics", "Catalyst Pharmaceuticals", "Crinetics Pharmaceuticals", "Cannabis Science", "Biogen", "Codex Labs", "Baxalta", "Acceleron Pharma", "Cytel", "BASF Plant Science", "Beam Therapeutics", "Acorda Therapeutics", "Akorn", "ACT Biotech Inc", "Cambrian Genomics", "ATyr Pharma", "Bioverativ", "Amarin Corporation", "BrainScope Company, Inc.", "Cubist Pharmaceuticals", "BioDuro", "Biovest", "Adaptimmune", "Clever Carnivore", "Cypress Systems", "American Biotech", "AquaBounty Technologies", "Athira Pharma", "Amylyx Pharmaceuticals", "Affymetrix", "Ablitech, Inc.", "Abbott Laboratories", "Arcadia Biosciences", "Celera Corporation", "Digene", "Colossal Biosciences", "Cofactor Genomics", "Crown Bioscience", "Apricus Biosciences", "Amylin Pharmaceuticals", "Array BioPharma", "ACell", "BioViva", "Arena Pharmaceuticals", "Counsyl", "BioAmber", "10x Genomics", "CancerVax", "Cerus Corporation", "Creative Diagnostics", "Bio-Synthesis, Inc.", "AgeX Therapeutics", "Axogen", "Avax Technologies", "Arcturus Therapeutics", "Agricen", "Biolex", "Agilent Technologies", "Delix Therapeutics", "Bio-Techne", "Catalent", "Danimer Scientific", "Dharmacon", "BioCryst Pharmaceuticals", "Dangerous Things", "BioMarin Pharmaceutical", "ATUM", "Ceres, Inc.", "Astellas Institute for Regenerative Medicine", "Cell Signaling Technology", "23andMe", "Adverum Biotechnologies", "Codexis", "Applera", "Celsense", "Dendreon", "AbbVie", "ALS Therapy Development Institute", "Corixa (company)", "Caliper Life Sciences", "Agenus", "Advaxis"], "jobs": [{"company": "10x Genomics", "title": "Staff Data Scientist, Marketing", "location": "Pleasanton, California, USA HQ", "url": "https://boards.greenhouse.io/10xgenomics/jobs/7664742?gh_jid=7664742", "date_posted": "2026-02-27", "ats": "Greenhouse"}, {"company": "Altos Labs", "title": "Machine Learning Engineer/Machine Learning Scientist , Multi Modality", "location": "San Diego, CA; San Francisco Bay Area, CA", "url": "https://job-boards.greenhouse.io/altoslabs/jobs/5709084004", "date_posted": "2026-03-31", "ats": "Greenhouse"}]}